[
  {
    "matched_key": "coherent.validator.character_consistency",
    "inject_to": "planner_system",
    "content": "[AUTO][coherent.validator.character_consistency] 修复策略（来自 guidance）\n- 强制角色一致性：同一人物脸型/发型/服装/主色调跨镜头保持一致；禁止漂移。\n- 强制风格一致性：统一调色/光照/材质/构图风格；禁止跨镜头风格跳变。",
    "source_reason_code": "coherent.validator.character_consistency",
    "source_experience_id": "exp_auto_45b817906007",
    "stats": {
      "success": 11,
      "fail": 0,
      "last_seen": "2026-03-21T15:39:23+00:00"
    },
    "confidence": 0.9231
  },
  {
    "matched_key": "brand.example.v1+char.xiaojiu.v1+coherent.validator.character_consistency",
    "confidence": 0.85,
    "inject_to": "planner_system",
    "content": "强制角色主色调锁定：#FF6B35；禁止跨镜头色调漂移；角色脸部与发型保持一致。",
    "source_experience_id": "exp_example_001",
    "source_reason_code": "coherent.validator.character_consistency",
    "stats": {
      "success": 0,
      "fail": 0,
      "last_seen": ""
    }
  },
  {
    "key": "*+*+cross_node.project_principle.memory_boundary",
    "inject_to": "planner_system",
    "content": "Memory sync boundary: public governance content (principles, standards, thresholds, debts) can sync across nodes. SOUL/USER/private memory must NOT sync. Extract-only policy for node_private.",
    "confidence": 0.8465,
    "source_experience_id": "github_nodeB-memory-sync-001",
    "source_reason_code": "cross_node.project_principle.memory_boundary",
    "baseline_version": 3,
    "admission_status": "probation",
    "stats": {
      "success": 4,
      "fail": 1,
      "hit_count": 5,
      "last_seen": "2026-04-07T12:01:35+00:00"
    },
    "created_at": 1775563241.7022302,
    "ttl_days": 0,
    "quarantined": true
  },
  {
    "key": "*+*+cross_node.reviewed_baseline.supply_chain_direction",
    "inject_to": "planner_system",
    "content": "Learning supply chain order: L2(manifest admission) -> L1(learning_latest snapshot) -> L3(admission quarantine). All entries require baseline_version + source_trace. No bypass allowed.",
    "confidence": 0.8465,
    "source_experience_id": "github_nodeB-supply-chain-001",
    "source_reason_code": "cross_node.reviewed_baseline.supply_chain_direction",
    "baseline_version": 4,
    "admission_status": "probation",
    "stats": {
      "success": 4,
      "fail": 1,
      "hit_count": 5,
      "last_seen": "2026-04-07T12:01:35+00:00"
    },
    "created_at": 1775563241.7022302,
    "ttl_days": 0,
    "quarantined": true
  },
  {
    "key": "*+*+github_learning.observability.3862fab3f05bc228",
    "inject_to": "planner_system",
    "content": "Automated observability: track agent performance, market impact, improvements over time. Key metrics dashboard + alerting on degradation.",
    "confidence": 0.8465,
    "source_experience_id": "github_3862fab3f05bc228",
    "source_reason_code": "github_learning.observability.3862fab3f05bc228",
    "baseline_version": 1,
    "admission_status": "active",
    "stats": {
      "success": 4,
      "fail": 1,
      "hit_count": 5,
      "last_seen": "2026-04-07T10:53:03+00:00"
    },
    "created_at": 1775559127.7202969,
    "ttl_days": 0,
    "quarantined": false
  },
  {
    "key": "*+*+github_learning.architecture.4774133980e77b07",
    "inject_to": "planner_system",
    "content": "Robust rollback mechanism: revert changes if performance declines or decisions lead to undesirable outcomes. Snapshot-based with automatic trigger on metric degradation.",
    "confidence": 0.8465,
    "source_experience_id": "github_4774133980e77b07",
    "source_reason_code": "github_learning.architecture.4774133980e77b07",
    "baseline_version": 2,
    "admission_status": "active",
    "stats": {
      "success": 4,
      "fail": 1,
      "hit_count": 5,
      "last_seen": "2026-04-07T10:53:03+00:00"
    },
    "created_at": 1775559127.7202969,
    "ttl_days": 0,
    "quarantined": false
  },
  {
    "key": "*+*+cross_node.project_principle.memory_boundary",
    "inject_to": "planner_system",
    "content": "Memory sync boundary: public governance content (principles, standards, thresholds, debts) can sync across nodes. SOUL/USER/private memory must NOT sync. Extract-only policy for node_private.",
    "confidence": 0.8465,
    "source_experience_id": "github_nodeB-memory-sync-001",
    "source_reason_code": "cross_node.project_principle.memory_boundary",
    "baseline_version": 3,
    "admission_status": "active",
    "stats": {
      "success": 4,
      "fail": 1,
      "hit_count": 5,
      "last_seen": "2026-04-07T12:01:35+00:00"
    },
    "created_at": 1775563241.7022302,
    "ttl_days": 0,
    "quarantined": false
  },
  {
    "key": "*+*+cross_node.reviewed_baseline.supply_chain_direction",
    "inject_to": "planner_system",
    "content": "Learning supply chain order: L2(manifest admission) -> L1(learning_latest snapshot) -> L3(admission quarantine). All entries require baseline_version + source_trace. No bypass allowed.",
    "confidence": 0.8465,
    "source_experience_id": "github_nodeB-supply-chain-001",
    "source_reason_code": "cross_node.reviewed_baseline.supply_chain_direction",
    "baseline_version": 4,
    "admission_status": "active",
    "stats": {
      "success": 4,
      "fail": 1,
      "hit_count": 5,
      "last_seen": "2026-04-07T12:01:35+00:00"
    },
    "created_at": 1775563241.7022302,
    "ttl_days": 0,
    "quarantined": false
  }
]